MANIFEST.in
README.rst
setup.py
aliyun_python_sdk_reid.egg-info/PKG-INFO
aliyun_python_sdk_reid.egg-info/SOURCES.txt
aliyun_python_sdk_reid.egg-info/dependency_links.txt
aliyun_python_sdk_reid.egg-info/requires.txt
aliyun_python_sdk_reid.egg-info/top_level.txt
aliyunsdkreid/__init__.py
aliyunsdkreid/endpoint.py
aliyunsdkreid/request/__init__.py
aliyunsdkreid/request/v20190928/DescribeBaseStatisticsRequest.py
aliyunsdkreid/request/v20190928/DescribeCameraStatisticsRequest.py
aliyunsdkreid/request/v20190928/DescribeCursorRequest.py
aliyunsdkreid/request/v20190928/DescribeCustomerFlowByLocationRequest.py
aliyunsdkreid/request/v20190928/DescribeDevicesRequest.py
aliyunsdkreid/request/v20190928/DescribeHeatMapRequest.py
aliyunsdkreid/request/v20190928/DescribeImageUrlsRequest.py
aliyunsdkreid/request/v20190928/DescribeIpcLiveAddressRequest.py
aliyunsdkreid/request/v20190928/DescribeOverviewDataRequest.py
aliyunsdkreid/request/v20190928/GetFootwearEventRequest.py
aliyunsdkreid/request/v20190928/GetFootwearPositionRequest.py
aliyunsdkreid/request/v20190928/ImportSpecialPersonnelRequest.py
aliyunsdkreid/request/v20190928/ListActionDataRequest.py
aliyunsdkreid/request/v20190928/ListDevicesImagesRequest.py
aliyunsdkreid/request/v20190928/ListEmapRequest.py
aliyunsdkreid/request/v20190928/ListLocationRequest.py
aliyunsdkreid/request/v20190928/ListMaskDetectionResultsRequest.py
aliyunsdkreid/request/v20190928/ListPersonByImageRequest.py
aliyunsdkreid/request/v20190928/ListStoreRequest.py
aliyunsdkreid/request/v20190928/PullActionDataRequest.py
aliyunsdkreid/request/v20190928/PullTakeShoesEventRequest.py
aliyunsdkreid/request/v20190928/PullTryOnShoesEventRequest.py
aliyunsdkreid/request/v20190928/__init__.py